<?xml version="1.0" encoding="UTF-8"?>
<!DOCTYPE mapper PUBLIC "-//mybatis.org//DTD Mapper 3.0//EN" "http://mybatis.org/dtd/mybatis-3-mapper.dtd">
<mapper namespace="com.ecommerce.mapper.SchemaAutoIncrementColumnsMapper">
  <resultMap id="BaseResultMap" type="com.ecommerce.model.SchemaAutoIncrementColumns">
    <!--
      WARNING - @mbg.generated
      This element is automatically generated by MyBatis Generator, do not modify.
      This element was generated on Fri Jul 18 07:23:13 HKT 2025.
    -->
    <result column="table_schema" jdbcType="VARCHAR" property="tableSchema" />
    <result column="table_name" jdbcType="VARCHAR" property="tableName" />
    <result column="column_name" jdbcType="VARCHAR" property="columnName" />
    <result column="is_signed" jdbcType="INTEGER" property="isSigned" />
    <result column="is_unsigned" jdbcType="INTEGER" property="isUnsigned" />
    <result column="max_value" jdbcType="BIGINT" property="maxValue" />
    <result column="auto_increment" jdbcType="BIGINT" property="autoIncrement" />
    <result column="auto_increment_ratio" jdbcType="DECIMAL" property="autoIncrementRatio" />
  </resultMap>
  <resultMap extends="BaseResultMap" id="ResultMapWithBLOBs" type="com.ecommerce.model.SchemaAutoIncrementColumnsWithBLOBs">
    <!--
      WARNING - @mbg.generated
      This element is automatically generated by MyBatis Generator, do not modify.
      This element was generated on Fri Jul 18 07:23:13 HKT 2025.
    -->
    <result column="data_type" jdbcType="LONGVARCHAR" property="dataType" />
    <result column="column_type" jdbcType="LONGVARCHAR" property="columnType" />
  </resultMap>
  <sql id="Example_Where_Clause">
    <!--
      WARNING - @mbg.generated
      This element is automatically generated by MyBatis Generator, do not modify.
      This element was generated on Fri Jul 18 07:23:13 HKT 2025.
    -->
    <where>
      <foreach collection="oredCriteria" item="criteria" separator="or">
        <if test="criteria.valid">
          <trim prefix="(" prefixOverrides="and" suffix=")">
            <foreach collection="criteria.criteria" item="criterion">
              <choose>
                <when test="criterion.noValue">
                  and ${criterion.condition}
                </when>
                <when test="criterion.singleValue">
                  and ${criterion.condition} #{criterion.value}
                </when>
                <when test="criterion.betweenValue">
                  and ${criterion.condition} #{criterion.value} and #{criterion.secondValue}
                </when>
                <when test="criterion.listValue">
                  and ${criterion.condition}
                  <foreach close=")" collection="criterion.value" item="listItem" open="(" separator=",">
                    #{listItem}
                  </foreach>
                </when>
              </choose>
            </foreach>
          </trim>
        </if>
      </foreach>
    </where>
  </sql>
  <sql id="Update_By_Example_Where_Clause">
    <!--
      WARNING - @mbg.generated
      This element is automatically generated by MyBatis Generator, do not modify.
      This element was generated on Fri Jul 18 07:23:13 HKT 2025.
    -->
    <where>
      <foreach collection="example.oredCriteria" item="criteria" separator="or">
        <if test="criteria.valid">
          <trim prefix="(" prefixOverrides="and" suffix=")">
            <foreach collection="criteria.criteria" item="criterion">
              <choose>
                <when test="criterion.noValue">
                  and ${criterion.condition}
                </when>
                <when test="criterion.singleValue">
                  and ${criterion.condition} #{criterion.value}
                </when>
                <when test="criterion.betweenValue">
                  and ${criterion.condition} #{criterion.value} and #{criterion.secondValue}
                </when>
                <when test="criterion.listValue">
                  and ${criterion.condition}
                  <foreach close=")" collection="criterion.value" item="listItem" open="(" separator=",">
                    #{listItem}
                  </foreach>
                </when>
              </choose>
            </foreach>
          </trim>
        </if>
      </foreach>
    </where>
  </sql>
  <sql id="Base_Column_List">
    <!--
      WARNING - @mbg.generated
      This element is automatically generated by MyBatis Generator, do not modify.
      This element was generated on Fri Jul 18 07:23:13 HKT 2025.
    -->
    table_schema, table_name, column_name, is_signed, is_unsigned, max_value, auto_increment, 
    auto_increment_ratio
  </sql>
  <sql id="Blob_Column_List">
    <!--
      WARNING - @mbg.generated
      This element is automatically generated by MyBatis Generator, do not modify.
      This element was generated on Fri Jul 18 07:23:13 HKT 2025.
    -->
    data_type, column_type
  </sql>
  <select id="selectByExampleWithBLOBs" parameterType="com.ecommerce.model.SchemaAutoIncrementColumnsExample" resultMap="ResultMapWithBLOBs">
    <!--
      WARNING - @mbg.generated
      This element is automatically generated by MyBatis Generator, do not modify.
      This element was generated on Fri Jul 18 07:23:13 HKT 2025.
    -->
    select
    <if test="distinct">
      distinct
    </if>
    <include refid="Base_Column_List" />
    ,
    <include refid="Blob_Column_List" />
    from schema_auto_increment_columns
    <if test="_parameter != null">
      <include refid="Example_Where_Clause" />
    </if>
    <if test="orderByClause != null">
      order by ${orderByClause}
    </if>
  </select>
  <select id="selectByExample" parameterType="com.ecommerce.model.SchemaAutoIncrementColumnsExample" resultMap="BaseResultMap">
    <!--
      WARNING - @mbg.generated
      This element is automatically generated by MyBatis Generator, do not modify.
      This element was generated on Fri Jul 18 07:23:13 HKT 2025.
    -->
    select
    <if test="distinct">
      distinct
    </if>
    <include refid="Base_Column_List" />
    from schema_auto_increment_columns
    <if test="_parameter != null">
      <include refid="Example_Where_Clause" />
    </if>
    <if test="orderByClause != null">
      order by ${orderByClause}
    </if>
  </select>
  <delete id="deleteByExample" parameterType="com.ecommerce.model.SchemaAutoIncrementColumnsExample">
    <!--
      WARNING - @mbg.generated
      This element is automatically generated by MyBatis Generator, do not modify.
      This element was generated on Fri Jul 18 07:23:13 HKT 2025.
    -->
    delete from schema_auto_increment_columns
    <if test="_parameter != null">
      <include refid="Example_Where_Clause" />
    </if>
  </delete>
  <insert id="insert" parameterType="com.ecommerce.model.SchemaAutoIncrementColumnsWithBLOBs">
    <!--
      WARNING - @mbg.generated
      This element is automatically generated by MyBatis Generator, do not modify.
      This element was generated on Fri Jul 18 07:23:13 HKT 2025.
    -->
    insert into schema_auto_increment_columns (table_schema, table_name, column_name, 
      is_signed, is_unsigned, max_value, 
      auto_increment, auto_increment_ratio, data_type, 
      column_type)
    values (#{tableSchema,jdbcType=VARCHAR}, #{tableName,jdbcType=VARCHAR}, #{columnName,jdbcType=VARCHAR}, 
      #{isSigned,jdbcType=INTEGER}, #{isUnsigned,jdbcType=INTEGER}, #{maxValue,jdbcType=BIGINT}, 
      #{autoIncrement,jdbcType=BIGINT}, #{autoIncrementRatio,jdbcType=DECIMAL}, #{dataType,jdbcType=LONGVARCHAR}, 
      #{columnType,jdbcType=LONGVARCHAR})
  </insert>
  <insert id="insertSelective" parameterType="com.ecommerce.model.SchemaAutoIncrementColumnsWithBLOBs">
    <!--
      WARNING - @mbg.generated
      This element is automatically generated by MyBatis Generator, do not modify.
      This element was generated on Fri Jul 18 07:23:13 HKT 2025.
    -->
    insert into schema_auto_increment_columns
    <trim prefix="(" suffix=")" suffixOverrides=",">
      <if test="tableSchema != null">
        table_schema,
      </if>
      <if test="tableName != null">
        table_name,
      </if>
      <if test="columnName != null">
        column_name,
      </if>
      <if test="isSigned != null">
        is_signed,
      </if>
      <if test="isUnsigned != null">
        is_unsigned,
      </if>
      <if test="maxValue != null">
        max_value,
      </if>
      <if test="autoIncrement != null">
        auto_increment,
      </if>
      <if test="autoIncrementRatio != null">
        auto_increment_ratio,
      </if>
      <if test="dataType != null">
        data_type,
      </if>
      <if test="columnType != null">
        column_type,
      </if>
    </trim>
    <trim prefix="values (" suffix=")" suffixOverrides=",">
      <if test="tableSchema != null">
        #{tableSchema,jdbcType=VARCHAR},
      </if>
      <if test="tableName != null">
        #{tableName,jdbcType=VARCHAR},
      </if>
      <if test="columnName != null">
        #{columnName,jdbcType=VARCHAR},
      </if>
      <if test="isSigned != null">
        #{isSigned,jdbcType=INTEGER},
      </if>
      <if test="isUnsigned != null">
        #{isUnsigned,jdbcType=INTEGER},
      </if>
      <if test="maxValue != null">
        #{maxValue,jdbcType=BIGINT},
      </if>
      <if test="autoIncrement != null">
        #{autoIncrement,jdbcType=BIGINT},
      </if>
      <if test="autoIncrementRatio != null">
        #{autoIncrementRatio,jdbcType=DECIMAL},
      </if>
      <if test="dataType != null">
        #{dataType,jdbcType=LONGVARCHAR},
      </if>
      <if test="columnType != null">
        #{columnType,jdbcType=LONGVARCHAR},
      </if>
    </trim>
  </insert>
  <select id="countByExample" parameterType="com.ecommerce.model.SchemaAutoIncrementColumnsExample" resultType="java.lang.Long">
    <!--
      WARNING - @mbg.generated
      This element is automatically generated by MyBatis Generator, do not modify.
      This element was generated on Fri Jul 18 07:23:13 HKT 2025.
    -->
    select count(*) from schema_auto_increment_columns
    <if test="_parameter != null">
      <include refid="Example_Where_Clause" />
    </if>
  </select>
  <update id="updateByExampleSelective" parameterType="map">
    <!--
      WARNING - @mbg.generated
      This element is automatically generated by MyBatis Generator, do not modify.
      This element was generated on Fri Jul 18 07:23:13 HKT 2025.
    -->
    update schema_auto_increment_columns
    <set>
      <if test="row.tableSchema != null">
        table_schema = #{row.tableSchema,jdbcType=VARCHAR},
      </if>
      <if test="row.tableName != null">
        table_name = #{row.tableName,jdbcType=VARCHAR},
      </if>
      <if test="row.columnName != null">
        column_name = #{row.columnName,jdbcType=VARCHAR},
      </if>
      <if test="row.isSigned != null">
        is_signed = #{row.isSigned,jdbcType=INTEGER},
      </if>
      <if test="row.isUnsigned != null">
        is_unsigned = #{row.isUnsigned,jdbcType=INTEGER},
      </if>
      <if test="row.maxValue != null">
        max_value = #{row.maxValue,jdbcType=BIGINT},
      </if>
      <if test="row.autoIncrement != null">
        auto_increment = #{row.autoIncrement,jdbcType=BIGINT},
      </if>
      <if test="row.autoIncrementRatio != null">
        auto_increment_ratio = #{row.autoIncrementRatio,jdbcType=DECIMAL},
      </if>
      <if test="row.dataType != null">
        data_type = #{row.dataType,jdbcType=LONGVARCHAR},
      </if>
      <if test="row.columnType != null">
        column_type = #{row.columnType,jdbcType=LONGVARCHAR},
      </if>
    </set>
    <if test="example != null">
      <include refid="Update_By_Example_Where_Clause" />
    </if>
  </update>
  <update id="updateByExampleWithBLOBs" parameterType="map">
    <!--
      WARNING - @mbg.generated
      This element is automatically generated by MyBatis Generator, do not modify.
      This element was generated on Fri Jul 18 07:23:13 HKT 2025.
    -->
    update schema_auto_increment_columns
    set table_schema = #{row.tableSchema,jdbcType=VARCHAR},
      table_name = #{row.tableName,jdbcType=VARCHAR},
      column_name = #{row.columnName,jdbcType=VARCHAR},
      is_signed = #{row.isSigned,jdbcType=INTEGER},
      is_unsigned = #{row.isUnsigned,jdbcType=INTEGER},
      max_value = #{row.maxValue,jdbcType=BIGINT},
      auto_increment = #{row.autoIncrement,jdbcType=BIGINT},
      auto_increment_ratio = #{row.autoIncrementRatio,jdbcType=DECIMAL},
      data_type = #{row.dataType,jdbcType=LONGVARCHAR},
      column_type = #{row.columnType,jdbcType=LONGVARCHAR}
    <if test="example != null">
      <include refid="Update_By_Example_Where_Clause" />
    </if>
  </update>
  <update id="updateByExample" parameterType="map">
    <!--
      WARNING - @mbg.generated
      This element is automatically generated by MyBatis Generator, do not modify.
      This element was generated on Fri Jul 18 07:23:13 HKT 2025.
    -->
    update schema_auto_increment_columns
    set table_schema = #{row.tableSchema,jdbcType=VARCHAR},
      table_name = #{row.tableName,jdbcType=VARCHAR},
      column_name = #{row.columnName,jdbcType=VARCHAR},
      is_signed = #{row.isSigned,jdbcType=INTEGER},
      is_unsigned = #{row.isUnsigned,jdbcType=INTEGER},
      max_value = #{row.maxValue,jdbcType=BIGINT},
      auto_increment = #{row.autoIncrement,jdbcType=BIGINT},
      auto_increment_ratio = #{row.autoIncrementRatio,jdbcType=DECIMAL}
    <if test="example != null">
      <include refid="Update_By_Example_Where_Clause" />
    </if>
  </update>
</mapper>